Workbook
Name aporte: APP!$D$21
Name patrimonio: APP!$D$24
Name qtd_anos: APP!$D$22
Name rendimento_carteira: APP!$D$17
Name salario: APP!$D$16
Name sugestao_investimento: APP!$D$18
Name taxa_mensal: APP!$D$23

Sheet APP
B15: CONFIGURAÇÕES
B16: Salário | D16: 2000
B17: Rendimento Carteira | D17: 0.006
B18: Sugestão de Investimento (30%) | D18: =D16*30% -> 600
B20: INVESTIMENTO MENSAL
B21: Quanto investir por mês? | D21: 200
B22: Por quantos anos? | D22: 5
B23: Taxa de rendimento mensal? | D23: 0.01079
B24: Patrimônio acumulado? | D24: =FV(taxa_mensal,qtd_anos*12,aporte)*-1 -> 16755.383
B25: Dividendos mensais? | D25: =patrimonio*rendimento_carteira -> 100.5323
B27: CENÁRIOS | D27: DIVIDENDO
A28: 2 | B28: Quanto em 2 Anos? | C28: =FV($D$23,$A28*12,$D$21*-1) -> 5445.5255 | D28: =C28*rendimento_carteira -> 32.673153
A29: 5 | B29: Quanto em 5 Anos? | C29: =FV($D$23,$A29*12,$D$21*-1) -> 16755.383 | D29: =C29*rendimento_carteira -> 100.5323
A30: 10 | B30: Quanto em 10 Anos? | C30: =FV($D$23,$A30*12,$D$21*-1) -> 48656.843 | D30: =C30*rendimento_carteira -> 291.94106
A31: 20 | B31: Quanto em 20 Anos? | C31: =FV($D$23,$A31*12,$D$21*-1) -> 225039.68 | D31: =C31*rendimento_carteira -> 1350.2381
A32: 30 | B32: Quanto em 30 Anos? | C32: =FV($D$23,$A32*12,$D$21*-1) -> 864433.93 | D32: =C32*rendimento_carteira -> 5186.6036
B36: Perfil | C36: Moderado
B37: VALOR A SER INVESTIDO POR MÊS | C37: =aporte -> 200
B39: TIPO DE FII | C39: Percentual Sugerido | D39: Valores
B40: PAPEL | C40: =VLOOKUP($C$36&"-"&B40,PLANILHA_PERFIS!$A:$D,4,FALSE) -> 0.32 | D40: =$C$37*C40 -> 64
B41: TIJOLO | C41: =VLOOKUP($C$36&"-"&B41,PLANILHA_PERFIS!$A:$D,4,FALSE) -> 0.35 | D41: =$C$37*C41 -> 70
B42: HÍBRIDOS | C42: =VLOOKUP($C$36&"-"&B42,PLANILHA_PERFIS!$A:$D,4,FALSE) -> 0.08 | D42: =$C$37*C42 -> 16
B43: FOFs | C43: =VLOOKUP($C$36&"-"&B43,PLANILHA_PERFIS!$A:$D,4,FALSE) -> 0.05 | D43: =$C$37*C43 -> 10
B44: DESENVOLVIMENTO | C44: =VLOOKUP($C$36&"-"&B44,PLANILHA_PERFIS!$A:$D,4,FALSE) -> 0.1 | D44: =$C$37*C44 -> 20
B45: HOTELARIAS | C45: =VLOOKUP($C$36&"-"&B45,PLANILHA_PERFIS!$A:$D,4,FALSE) -> 0.1 | D45: =$C$37*C45 -> 20
D46: =SUM(D40:D45) -> 200

Sheet PLANILHA_PERFIS
A2: CHAVE | B2: PERFIL | C2: TIPO DE FII | D2: %
A3: =B3&"-"&C3 -> Conservador-PAPEL | B3: Conservador | C3: PAPEL | D3: 0.3 | H3: %
A4: =B4&"-"&C4 -> Conservador-TIJOLO | B4: Conservador | C4: TIJOLO | D4: 0.5 | G4: Moderado-TIJOLO | H4: =VLOOKUP(G4,$A:$D,4,) -> 0.35
A5: =B5&"-"&C5 -> Conservador-HÍBRIDOS | B5: Conservador | C5: HÍBRIDOS | D5: 0.1
A6: =B6&"-"&C6 -> Conservador-FOFs | B6: Conservador | C6: FOFs | D6: 0.1
A7: =B7&"-"&C7 -> Conservador-DESENVOLVIMENTO | B7: Conservador | C7: DESENVOLVIMENTO | D7: 0
A8: =B8&"-"&C8 -> Conservador-HOTELARIAS | B8: Conservador | C8: HOTELARIAS | D8: 0
A9: =B9&"-"&C9 -> Moderado-PAPEL | B9: Moderado | C9: PAPEL | D9: 0.32
A10: =B10&"-"&C10 -> Moderado-TIJOLO | B10: Moderado | C10: TIJOLO | D10: 0.35
A11: =B11&"-"&C11 -> Moderado-HÍBRIDOS | B11: Moderado | C11: HÍBRIDOS | D11: 0.08
A12: =B12&"-"&C12 -> Moderado-FOFs | B12: Moderado | C12: FOFs | D12: 0.05
A13: =B13&"-"&C13 -> Moderado-DESENVOLVIMENTO | B13: Moderado | C13: DESENVOLVIMENTO | D13: 0.1
A14: =B14&"-"&C14 -> Moderado-HOTELARIAS | B14: Moderado | C14: HOTELARIAS | D14: 0.1
A15: =B15&"-"&C15 -> Agressivo-PAPEL | B15: Agressivo | C15: PAPEL | D15: 0.5
A16: =B16&"-"&C16 -> Agressivo-TIJOLO | B16: Agressivo | C16: TIJOLO | D16: 0.1
... A20: =B20&"-"&C20 -> Agressivo-HOTELARIAS | B20: Agressivo | C20: HOTELARIAS | D20: 0.1
